epicore-0.1.7.dist-info/licenses/LICENSE
epicore_utils/__init__.py
epicore_utils/epicore_main.py
epicore_utils/modules/compute_cores.py
epicore_utils/modules/generate_report.py
epicore_utils/modules/locserver.py
epicore_utils/modules/map_result.py
epicore_utils/modules/parse_input.py
epicore_utils/modules/visualize_protein.py
epicore-0.1.7.dist-info/METADATA
epicore-0.1.7.dist-info/WHEEL
epicore-0.1.7.dist-info/entry_points.txt
epicore-0.1.7.dist-info/top_level.txt
epicore-0.1.7.dist-info/RECORD
