Metadata-Version: 2.4
Name: epicore
Version: 0.1.7
Summary: Compute core epitopes from multiple overlapping peptides.
Author-email: Jana Hoffmann <epicore_jana@family-hoffmann.de>
License: MIT license
Project-URL: Repository, https://github.com/AG-Walz/epicore
Keywords: peptides,epitopes,core epitopes
Classifier: Programming Language :: Python :: 3
Classifier: Programming Language :: Python :: 3.10
Requires-Python: >=3.10
License-File: LICENSE
Requires-Dist: biopython>=1.80
Requires-Dist: click>=8.1
Requires-Dist: matplotlib>=3.4
Requires-Dist: numpy>=2
Requires-Dist: pandas>=2
Requires-Dist: pyyaml>=6.0.2
Requires-Dist: openpyxl>=3.1.3
Dynamic: license-file
